MANIFEST.in
README.rst
setup.py
Products/__init__.py
Products.PloneboardNotify.egg-info/PKG-INFO
Products.PloneboardNotify.egg-info/SOURCES.txt
Products.PloneboardNotify.egg-info/dependency_links.txt
Products.PloneboardNotify.egg-info/entry_points.txt
Products.PloneboardNotify.egg-info/namespace_packages.txt
Products.PloneboardNotify.egg-info/not-zip-safe
Products.PloneboardNotify.egg-info/requires.txt
Products.PloneboardNotify.egg-info/top_level.txt
Products/PloneboardNotify/README.txt
Products/PloneboardNotify/__init__.py
Products/PloneboardNotify/configure.zcml
Products/PloneboardNotify/html_template.py
Products/PloneboardNotify/interfaces.py
Products/PloneboardNotify/Extensions/install.py
Products/PloneboardNotify/browser/Locale.gif
Products/PloneboardNotify/browser/__init__.py
Products/PloneboardNotify/browser/bell_board.gif
Products/PloneboardNotify/browser/configure.zcml
Products/PloneboardNotify/browser/ploneboard_notification.pt
Products/PloneboardNotify/browser/ploneboard_notification.py
Products/PloneboardNotify/browser/ploneboard_notification_forum.pt
Products/PloneboardNotify/browser/ploneboard_notification_forum.py
Products/PloneboardNotify/events/__init__.py
Products/PloneboardNotify/events/configure.zcml
Products/PloneboardNotify/events/notify.py
Products/PloneboardNotify/locales/Products.PloneboardNotify-manual.pot
Products/PloneboardNotify/locales/Products.PloneboardNotify.pot
Products/PloneboardNotify/locales/runi18ndude.sh
Products/PloneboardNotify/locales/es/LC_MESSAGES/Products.PloneboardNotify.po
Products/PloneboardNotify/locales/fr/LC_MESSAGES/Products.PloneboardNotify.po
Products/PloneboardNotify/locales/it/LC_MESSAGES/Products.PloneboardNotify.po
Products/PloneboardNotify/locales/ru/LC_MESSAGES/Products.PloneboardNotify.po
Products/PloneboardNotify/profiles/default/controlpanel.xml
Products/PloneboardNotify/profiles/default/metadata.xml
Products/PloneboardNotify/profiles/default/propertiestool.xml
Products/PloneboardNotify/profiles/uninstall/controlpanel.xml
Products/PloneboardNotify/tests/__init__.py
Products/PloneboardNotify/tests/base.py
Products/PloneboardNotify/tests/test_doctest.py
docs/HISTORY.txt
docs/INSTALL.txt
docs/LICENSE.GPL
docs/LICENSE.txt