Metadata-Version: 1.1
Name: Products.PloneboardNotify
Version: 0.5.0
Summary: A configurable Plone product for sending e-mails when new messages are added to Ploneboard forums
Home-page: http://plone.org/products/ploneboardnotify
Author: keul
Author-email: luca@keul.it
License: GPL
Keywords: ploneboard forum notify email
Platform: UNKNOWN
Classifier: Framework :: Plone
Classifier: Framework :: Plone :: 4.0
Classifier: Framework :: Plone :: 4.1
Classifier: Framework :: Plone :: 4.2
Classifier: Framework :: Plone :: 4.3
Classifier: Programming Language :: Python
Classifier: Development Status :: 4 - Beta
Classifier: Topic :: Software Development :: Libraries :: Python Modules
